mypythontools/__init__.py
mypythontools/config/__init__.py
mypythontools/config/config_internal.py
mypythontools/misc/__init__.py
mypythontools/misc/misc_internal.py
mypythontools/paths/__init__.py
mypythontools/paths/paths_internal.py
mypythontools/paths/wsl_paths.py
mypythontools/plots/__init__.py
mypythontools/plots/plots_internal.py
mypythontools/property/__init__.py
mypythontools/property/property_internal.py
mypythontools/system/__init__.py
mypythontools/system/system_internal.py
mypythontools/types/__init__.py
mypythontools/types/type_conversions_internal.py
mypythontools/types/type_hints_internal.py
mypythontools/types/validation.py
mypythontools-3.0.2.dist-info/LICENSE
mypythontools-3.0.2.dist-info/METADATA
mypythontools-3.0.2.dist-info/WHEEL
mypythontools-3.0.2.dist-info/top_level.txt
mypythontools-3.0.2.dist-info/RECORD
