Metadata-Version: 2.1
Name: mypythontools
Version: 3.0.2
Summary: Some tools/functions/snippets used across projects.
Home-page: https://github.com/Malachov/mypythontools
Author: Daniel Malachov
Author-email: malachovd@seznam.cz
License: mit
Platform: any
Classifier: Development Status :: 3 - Alpha
Classifier: Environment :: Other Environment
Classifier: Intended Audience :: Developers
Classifier: Intended Audience :: Education
Classifier: License :: OSI Approved :: MIT License
Classifier: Natural Language :: English
Classifier: Operating System :: OS Independent
Classifier: Programming Language :: Python :: 3.7
Classifier: Programming Language :: Python :: 3.9
Classifier: Programming Language :: Python :: 3.10
Classifier: Programming Language :: Python :: 3.11
Classifier: Programming Language :: Python
Classifier: Topic :: Software Development :: Libraries :: Application Frameworks
Classifier: Topic :: Software Development :: Libraries :: Python Modules
Requires-Python: >=3.7
License-File: LICENSE
Requires-Dist: mylogging (~=4.0.6)
Requires-Dist: tabulate
Requires-Dist: typeguard
Provides-Extra: all
Requires-Dist: IPython ; extra == 'all'
Requires-Dist: matplotlib ; extra == 'all'
Requires-Dist: pandas ; extra == 'all'
Requires-Dist: plotly ; extra == 'all'
Provides-Extra: plots
Requires-Dist: IPython ; extra == 'plots'
Requires-Dist: matplotlib ; extra == 'plots'
Requires-Dist: pandas ; extra == 'plots'
Requires-Dist: plotly ; extra == 'plots'
